dev_kit_mcp_server/__init__.py
dev_kit_mcp_server/__main__.py
dev_kit_mcp_server/cli.py
dev_kit_mcp_server/create_server.py
dev_kit_mcp_server/custom_fastmcp.py
dev_kit_mcp_server/fastmcp_server.py
dev_kit_mcp_server/tool_factory.py
dev_kit_mcp_server/core/__init__.py
dev_kit_mcp_server/core/base_op.py
dev_kit_mcp_server/tools/__init__.py
dev_kit_mcp_server/tools/commands/__init__.py
dev_kit_mcp_server/tools/commands/base.py
dev_kit_mcp_server/tools/commands/make_target.py
dev_kit_mcp_server/tools/commands/predefined.py
dev_kit_mcp_server/tools/explore/__init__.py
dev_kit_mcp_server/tools/explore/read_lines.py
dev_kit_mcp_server/tools/explore/search_files.py
dev_kit_mcp_server/tools/explore/search_text.py
dev_kit_mcp_server/tools/file_sys/__init__.py
dev_kit_mcp_server/tools/file_sys/create.py
dev_kit_mcp_server/tools/file_sys/edit.py
dev_kit_mcp_server/tools/file_sys/move.py
dev_kit_mcp_server/tools/file_sys/remove.py
dev_kit_mcp_server/tools/file_sys/rename.py
dev_kit_mcp_server/tools/git/__init__.py
dev_kit_mcp_server/tools/git/add.py
dev_kit_mcp_server/tools/git/checkout.py
dev_kit_mcp_server/tools/git/commit.py
dev_kit_mcp_server/tools/git/create_branch.py
dev_kit_mcp_server/tools/git/diff.py
dev_kit_mcp_server/tools/git/pull.py
dev_kit_mcp_server/tools/git/push.py
dev_kit_mcp_server/tools/git/status.py
dkmcp_utils/__init__.py
dev_kit_mcp_server-0.1.5b0.dist-info/METADATA
dev_kit_mcp_server-0.1.5b0.dist-info/WHEEL
dev_kit_mcp_server-0.1.5b0.dist-info/entry_points.txt
dev_kit_mcp_server-0.1.5b0.dist-info/licenses/LICENSE
dev_kit_mcp_server-0.1.5b0.dist-info/RECORD
